checkpointed_steps/__init__.py
checkpointed_steps/bases.py
checkpointed_steps/builders.py
checkpointed_steps/data_formats.py
checkpointed_steps/data_loaders/__init__.py
checkpointed_steps/data_loaders/csv.py
checkpointed_steps/data_loaders/dictionary.py
checkpointed_steps/data_loaders/fasttext.py
checkpointed_steps/data_loaders/glove.py
checkpointed_steps/data_loaders/json.py
checkpointed_steps/data_loaders/shared.py
checkpointed_steps/data_loaders/word2vec.py
checkpointed_steps/encoders/__init__.py
checkpointed_steps/encoders/text/__init__.py
checkpointed_steps/encoders/text/count.py
checkpointed_steps/encoders/text/dict2array.py
checkpointed_steps/encoders/text/dictionary.py
checkpointed_steps/encoders/text/huggingface.py
checkpointed_steps/encoders/text/sentence_transformers.py
checkpointed_steps/encoders/text/tfidf.py
checkpointed_steps/encoders/text/word2vec.py
checkpointed_steps/misc/__init__.py
checkpointed_steps/misc/func.py
checkpointed_steps/models/__init__.py
checkpointed_steps/models/unsupervised/__init__.py
checkpointed_steps/models/unsupervised/clustering/__init__.py
checkpointed_steps/models/unsupervised/clustering/hdbscan.py
checkpointed_steps/models/unsupervised/dimensionality_reduction/__init__.py
checkpointed_steps/models/unsupervised/dimensionality_reduction/umap.py
checkpointed_steps/models/unsupervised/text/__init__.py
checkpointed_steps/models/unsupervised/text/lda.py
checkpointed_steps/models/unsupervised/text/lsi.py
checkpointed_steps/plotting/__init__.py
checkpointed_steps/plotting/scatter.py
checkpointed_steps/processing/__init__.py
checkpointed_steps/processing/text/__init__.py
checkpointed_steps/processing/text/casing.py
checkpointed_steps/processing/text/contractions.py
checkpointed_steps/processing/text/df.py
checkpointed_steps/processing/text/df_filter.py
checkpointed_steps/processing/text/flatten.py
checkpointed_steps/processing/text/lemmatization.py
checkpointed_steps/processing/text/part_of_speech.py
checkpointed_steps-0.2.0.dist-info/LICENSE
checkpointed_steps-0.2.0.dist-info/METADATA
checkpointed_steps-0.2.0.dist-info/WHEEL
checkpointed_steps-0.2.0.dist-info/top_level.txt
checkpointed_steps-0.2.0.dist-info/RECORD
