Metadata-Version: 2.1
Name: checkpointed-steps
Version: 0.2.0
Author-email: Jesse Maarleveld <jessemaarleveld@gmail.com>
Maintainer-email: Jesse Maarleveld <jessemaarleveld@gmail.com>
License: GNU GENERAL PUBLIC LICENSE
Requires-Python: >=3.10
License-File: LICENSE
Requires-Dist: checkpointed-core >=1.0
Requires-Dist: pandas
Requires-Dist: gensim
Requires-Dist: numpy
Requires-Dist: nltk
Requires-Dist: contractions
Requires-Dist: scipy
Requires-Dist: scikit-learn
Requires-Dist: torch ==2.1.2
Requires-Dist: transformers
Requires-Dist: sentence-transformers
Requires-Dist: umap-learn
Requires-Dist: hdbscan
Requires-Dist: matplotlib
Requires-Dist: seaborn
